<annotation>
	<folder>train_pic</folder>
	<filename>pic_219.png</filename>
	<path>E:\work\python_code\verification_code_detection\train\train_pic\pic_219.png</path>
	<source>
		<database>Unknown</database>
	</source>
	<size>
		<width>242</width>
		<height>198</height>
		<depth>3</depth>
	</size>
	<segmented>0</segmented>
	<object>
		<name>usave</name>
		<pose>Unspecified</pose>
		<truncated>0</truncated>
		<difficult>0</difficult>
		<bndbox>
			<xmin>100</xmin>
			<ymin>50</ymin>
			<xmax>148</xmax>
			<ymax>99</ymax>
		</bndbox>
	</object>
	<object>
		<name>heart</name>
		<pose>Unspecified</pose>
		<truncated>0</truncated>
		<difficult>0</difficult>
		<bndbox>
			<xmin>195</xmin>
			<ymin>50</ymin>
			<xmax>238</xmax>
			<ymax>95</ymax>
		</bndbox>
	</object>
	<object>
		<name>planet</name>
		<pose>Unspecified</pose>
		<truncated>0</truncated>
		<difficult>0</difficult>
		<bndbox>
			<xmin>102</xmin>
			<ymin>146</ymin>
			<xmax>145</xmax>
			<ymax>190</ymax>
		</bndbox>
	</object>
</annotation>
